e2xgrader_cells/__init__.py
e2xgrader_cells/_version.py
e2xgrader_cells-0.1.1.data/data/share/jupyter/labextensions/@e2xgrader/cells/package.json
e2xgrader_cells-0.1.1.data/data/share/jupyter/labextensions/@e2xgrader/cells/schemas/@e2xgrader/cells/factory.json
e2xgrader_cells-0.1.1.data/data/share/jupyter/labextensions/@e2xgrader/cells/schemas/@e2xgrader/cells/package.json.orig
e2xgrader_cells-0.1.1.data/data/share/jupyter/labextensions/@e2xgrader/cells/static/357.2f864b1633ca3081f547.js
e2xgrader_cells-0.1.1.data/data/share/jupyter/labextensions/@e2xgrader/cells/static/728.31edb563f84c4535ddf9.js
e2xgrader_cells-0.1.1.data/data/share/jupyter/labextensions/@e2xgrader/cells/static/remoteEntry.3b79f2d647032a159163.js
e2xgrader_cells-0.1.1.data/data/share/jupyter/labextensions/@e2xgrader/cells/static/style.js
e2xgrader_cells-0.1.1.data/data/share/jupyter/labextensions/@e2xgrader/cells/static/third-party-licenses.json
e2xgrader_cells-0.1.1.data/data/share/jupyter/labextensions/@e2xgrader/cells/install.json
e2xgrader_cells-0.1.1.dist-info/METADATA
e2xgrader_cells-0.1.1.dist-info/WHEEL
e2xgrader_cells-0.1.1.dist-info/licenses/LICENSE
e2xgrader_cells-0.1.1.dist-info/RECORD
